nbtoolbelt/__init__.py
nbtoolbelt/__main__.py
nbtoolbelt/_version.py
nbtoolbelt/arguments.py
nbtoolbelt/cleaning.py
nbtoolbelt/config.py
nbtoolbelt/counting.py
nbtoolbelt/inline_attachments.py
nbtoolbelt/nbcatapp.py
nbtoolbelt/nbcleanapp.py
nbtoolbelt/nbdumpapp.py
nbtoolbelt/nbheadapp.py
nbtoolbelt/nbpunchapp.py
nbtoolbelt/nbrunapp.py
nbtoolbelt/nbsplitapp.py
nbtoolbelt/nbstatsapp.py
nbtoolbelt/nbvalidateapp.py
nbtoolbelt/nbviewapp.py
nbtoolbelt/notebook_io.py
nbtoolbelt/printing.py
nbtoolbelt/processing.py
nbtoolbelt/punching.py
nbtoolbelt/rendering.py
nbtoolbelt/running.py
nbtoolbelt/toolbaseapp.py
nbtoolbelt/validating.py
nbtoolbelt/data/nbtoolbelt.json
nbtoolbelt-2024.7.2.dist-info/LICENSE.txt
nbtoolbelt-2024.7.2.dist-info/METADATA
nbtoolbelt-2024.7.2.dist-info/WHEEL
nbtoolbelt-2024.7.2.dist-info/entry_points.txt
nbtoolbelt-2024.7.2.dist-info/top_level.txt
nbtoolbelt-2024.7.2.dist-info/RECORD
