Metadata-Version: 2.1
Name: nbtoolbelt
Version: 2024.7.2
Summary: Tools to work with Jupyter notebooks
Author-email: "Tom Verhoeff (Eindhoven Univesity of Technology)" <T.Verhoeff@tue.nl>
License: MIT License
Project-URL: Homepage, https://gitlab.tue.nl/jupyter-projects/nbtoolbelt
Project-URL: Documentation, https://nbtoolbelt.readthedocs.io/
Project-URL: Source, https://gitlab.tue.nl/jupyter-projects/nbtoolbelt/
Project-URL: Issues, https://gitlab.tue.nl/jupyter-projects/nbtoolbelt/-/issues
Project-URL: Changelog, https://gitlab.tue.nl/jupyter-projects/nbtoolbelt/-/blob/master/CHANGELOG.rst
Keywords: Jupyter notebooks,software tools,education
Classifier: Development Status :: 5 - Production/Stable
Classifier: Intended Audience :: Developers
Classifier: Intended Audience :: System Administrators
Classifier: Intended Audience :: Education
Classifier: Intended Audience :: Science/Research
Classifier: Topic :: Education
Classifier: Topic :: Scientific/Engineering
Classifier: Topic :: Software Development :: Libraries
Classifier: Topic :: Utilities
Classifier: License :: OSI Approved :: MIT License
Classifier: Programming Language :: Python
Classifier: Programming Language :: Python :: 3.9
Classifier: Programming Language :: Python :: 3.10
Classifier: Programming Language :: Python :: 3.11
Classifier: Programming Language :: Python :: 3.12
Classifier: Framework :: Jupyter
Classifier: Operating System :: OS Independent
Requires-Python: >=3.9
License-File: LICENSE.txt
Requires-Dist: nbformat~=5.9
Requires-Dist: nbconvert~=7.10
Requires-Dist: jupyter-client~=8.6
Requires-Dist: numpy~=1.26
Requires-Dist: pandas~=2.1
Provides-Extra: docs
Requires-Dist: sphinx~=5.0; extra == "docs"
Requires-Dist: sphinx-rtd-theme~=1.0; extra == "docs"
Requires-Dist: recommonmark~=0.7; extra == "docs"
Provides-Extra: test
Requires-Dist: pytest~=6.0; extra == "test"
Requires-Dist: pytest-mock~=3.5; extra == "test"
Requires-Dist: pytest-cov~=2.12; extra == "test"
Requires-Dist: ipykernel~=6.29; extra == "test"
